lookfor/__init__.py
lookfor/lookfor.py
lf_lookfor-1.0.0.dist-info/LICENSE
lf_lookfor-1.0.0.dist-info/METADATA
lf_lookfor-1.0.0.dist-info/WHEEL
lf_lookfor-1.0.0.dist-info/entry_points.txt
lf_lookfor-1.0.0.dist-info/top_level.txt
lf_lookfor-1.0.0.dist-info/RECORD
