Metadata-Version: 2.1
Name: lf-lookfor
Version: 1.0.0
Summary: look for things
Home-page: https://github.com/breakthatbass/lookfor
Author: Taylor Gamache
Author-email: gamache.taylor@gmail.com
License: MIT
Platform: UNKNOWN
Requires-Dist: termcolor
